alibabacloud_tea_util/__init__.py
alibabacloud_tea_util/client.py
alibabacloud_tea_util/models.py
alibabacloud_tea_util-0.3.14.dist-info/METADATA
alibabacloud_tea_util-0.3.14.dist-info/WHEEL
alibabacloud_tea_util-0.3.14.dist-info/top_level.txt
alibabacloud_tea_util-0.3.14.dist-info/RECORD
